sunkit_image/__init__.py
sunkit_image/_version.py
sunkit_image/asda.py
sunkit_image/coalignment.py
sunkit_image/conftest.py
sunkit_image/enhance.py
sunkit_image/granule.py
sunkit_image/radial.py
sunkit_image/stara.py
sunkit_image/time_lag.py
sunkit_image/trace.py
sunkit_image/version.py
sunkit_image/data/README.rst
sunkit_image/data/__init__.py
sunkit_image/data/test/IDL.txt
sunkit_image/data/test/__init__.py
sunkit_image/data/test/aia_171_cutout.fits
sunkit_image/data/test/asda_correct.npz
sunkit_image/data/test/asda_vxvy.npz
sunkit_image/data/test/dkist_photosphere.fits
sunkit_image/data/test/hmi_continuum_test_lowres_data.fits
sunkit_image/tests/__init__.py
sunkit_image/tests/figure_hashes_mpl_390_ft_261_sunpy_600_astropy_610.json
sunkit_image/tests/helpers.py
sunkit_image/tests/test_asda.py
sunkit_image/tests/test_coalignment.py
sunkit_image/tests/test_enhance.py
sunkit_image/tests/test_granule.py
sunkit_image/tests/test_radial.py
sunkit_image/tests/test_stara.py
sunkit_image/tests/test_time_lag.py
sunkit_image/tests/test_trace.py
sunkit_image/utils/__init__.py
sunkit_image/utils/decorators.py
sunkit_image/utils/noise.py
sunkit_image/utils/utils.py
sunkit_image/utils/tests/__init__.py
sunkit_image/utils/tests/test_noise.py
sunkit_image/utils/tests/test_utils.py
sunkit_image-0.6.1.dist-info/LICENSE.rst
sunkit_image-0.6.1.dist-info/METADATA
sunkit_image-0.6.1.dist-info/WHEEL
sunkit_image-0.6.1.dist-info/top_level.txt
sunkit_image-0.6.1.dist-info/RECORD
